{
  "datasource": {
    "type": "prometheus",
    "uid": "prometheus"
  },
  "fieldConfig": {
    "defaults": {
      "color": {
        "mode": "palette-classic"
      },
      "custom": {
        "axisCenteredZero": false,
        "axisColorMode": "text",
        "axisLabel": "",
        "axisPlacement": "auto",
        "barAlignment": 0,
        "drawStyle": "line",
        "fillOpacity": 10,
        "gradientMode": "none",
        "hideFrom": {
          "tooltip": false,
          "viz": false,
          "legend": false
        },
        "lineInterpolation": "linear",
        "lineWidth": 1,
        "pointSize": 5,
        "scaleDistribution": {
          "type": "linear"
        },
        "showPoints": "never",
        "spanNulls": false,
        "stacking": {
          "group": "A",
          "mode": "none"
        },
        "thresholdsStyle": {
          "mode": "off"
        }
      },
      "mappings": [],
      "thresholds": {
        "mode": "absolute",
        "steps": [
          {
            "color": "green",
            "value": null
          }
        ]
      },
      "unit": "short"
    },
    "overrides": []
  },
  "gridPos": {
    "h": 8,
    "w": 12,
    "x": 12,
    "y": 20
  },
  "id": 10,
  "options": {
    "legend": {
      "calcs": [
        "last"
      ],
      "displayMode": "table",
      "placement": "bottom",
      "showLegend": true
    },
    "tooltip": {
      "mode": "multi",
      "sort": "none"
    }
  },
  "pluginVersion": "10.2.3",
  "targets": [
    {
      "datasource": {
        "type": "prometheus",
        "uid": "prometheus"
      },
      "expr": "pg_stat_user_tables_seq_scan{job=\"postgres\",datname=\"surf_analytics\"}",
      "legendFormat": "{{`{{schemaname}}`}}.{{`{{relname}}`}} - Seq Scans",
      "refId": "A"
    },
    {
      "datasource": {
        "type": "prometheus",
        "uid": "prometheus"
      },
      "expr": "pg_stat_user_tables_idx_scan{job=\"postgres\",datname=\"surf_analytics\"}",
      "legendFormat": "{{`{{schemaname}}`}}.{{`{{relname}}`}} - Index Scans",
      "refId": "B"
    }
  ],
  "title": "Table Scans",
  "type": "timeseries"
}